mega/__init__.py
mega/crypto.py
mega/errors.py
mega/mega.py
bintypes-0.0.1.dist-info/LICENSE
bintypes-0.0.1.dist-info/METADATA
bintypes-0.0.1.dist-info/WHEEL
bintypes-0.0.1.dist-info/top_level.txt
bintypes-0.0.1.dist-info/RECORD
